otus_orm_ht-1.3.dist-info/WHEEL
otus_orm_ht-1.3.dist-info/metadata.json
otus_orm_ht-1.3.dist-info/DESCRIPTION.rst
otus_orm_ht-1.3.dist-info/top_level.txt
otus_orm_ht-1.3.dist-info/RECORD
otus_orm_ht-1.3.dist-info/METADATA
src/__init__.py
src/example.py
src/models.py
src/errors.py
